rustyfresh-1.0.0.dist-info/METADATA
rustyfresh-1.0.0.dist-info/WHEEL
rustyfresh-1.0.0.dist-info/license_files/LICENSE.txt
rustyfresh/__init__.py
rustyfresh/rustyfresh.cpython-311-x86_64-linux-gnu.so
rustyfresh-1.0.0.dist-info/RECORD
